pyvdp/__init__.py
pyvdp/configuration.ini.example
pyvdp/configuration.py
pyvdp/dispatcher.py
pyvdp/exceptions.py
pyvdp/logger.py
pyvdp/dcas/__init__.py
pyvdp/dcas/dispatcher.py
pyvdp/dcas/cardinquiry/__init__.py
pyvdp/dcas/cardinquiry/accounts/__init__.py
pyvdp/dcas/cardinquiry/accounts/debitcardinquiry.py
pyvdp/dcas/cardinquiry/accounts/models.py
pyvdp/forexrates/__init__.py
pyvdp/forexrates/dispatcher.py
pyvdp/forexrates/foreignexchangerates.py
pyvdp/forexrates/models.py
pyvdp/globalatmlocator/__init__.py
pyvdp/globalatmlocator/dispatcher.py
pyvdp/globalatmlocator/localatms/__init__.py
pyvdp/globalatmlocator/localatms/atmsinquiry.py
pyvdp/globalatmlocator/localatms/geocodesinquiry.py
pyvdp/globalatmlocator/localatms/models.py
pyvdp/globalatmlocator/localatms/routesinquiry.py
pyvdp/globalatmlocator/localatms/totalsinquiry.py
pyvdp/merchantlocator/__init__.py
pyvdp/merchantlocator/dispatcher.py
pyvdp/merchantlocator/locator.py
pyvdp/merchantlocator/models.py
pyvdp/merchantmeasurement/__init__.py
pyvdp/merchantmeasurement/dispatcher.py
pyvdp/merchantmeasurement/merchantbenchmark.py
pyvdp/merchantmeasurement/models.py
pyvdp/merchantsearch/__init__.py
pyvdp/merchantsearch/dispatcher.py
pyvdp/merchantsearch/models.py
pyvdp/merchantsearch/search.py
pyvdp/mlc/__init__.py
pyvdp/mlc/dispatcher.py
pyvdp/mlc/enrollment/__init__.py
pyvdp/mlc/enrollment/enrollments.py
pyvdp/mlc/enrollment/models.py
pyvdp/mlc/locationupdate/__init__.py
pyvdp/mlc/locationupdate/locations.py
pyvdp/mlc/locationupdate/models.py
pyvdp/paai/__init__.py
pyvdp/paai/dispatcher.py
pyvdp/paai/models.py
pyvdp/paai/fundstransferattinq/__init__.py
pyvdp/paai/fundstransferattinq/cardattributes/__init__.py
pyvdp/paai/fundstransferattinq/cardattributes/fundstransferinquiry.py
pyvdp/paai/fundstransferattinq/cardattributes/models.py
pyvdp/paai/generalattinq/__init__.py
pyvdp/paai/generalattinq/cardattributes/__init__.py
pyvdp-1.2.0.dist-info/DESCRIPTION.rst
pyvdp-1.2.0.dist-info/METADATA
pyvdp-1.2.0.dist-info/RECORD
pyvdp-1.2.0.dist-info/WHEEL
pyvdp-1.2.0.dist-info/metadata.json
pyvdp-1.2.0.dist-info/top_level.txt
