Metadata-Version: 2.0
Name: pyvdp
Version: 1.2.0
Summary: PyVDP: VISA APIs. Wrapped in Python.
Home-page: https://www.github.com/ppokrovsky/pyvdp
Author: Pavel Pokrovskiy
Author-email: ppokrovsky@gmail.com
License: MIT
Keywords: visa,vdp,payment
Platform: OS Independent
Classifier: Environment :: Web Environment
Classifier: Intended Audience :: Developers
Classifier: License :: OSI Approved :: MIT License
Classifier: Operating System :: OS Independent
Classifier: Programming Language :: Python
Classifier: Topic :: Software Development :: Libraries :: Python Modules
Classifier: Programming Language :: Python :: 2.7
Classifier: Programming Language :: Python :: 3.3
Classifier: Programming Language :: Python :: 3.4
Classifier: Programming Language :: Python :: 3.5
Classifier: Programming Language :: Python :: 3.6
Requires-Dist: jsonpickle
Requires-Dist: requests
Requires-Dist: setuptools
Requires-Dist: six
